{
	"item:slug:electric-arc": [
		{
			"trigger": "damage-roll",
			"contents": [
				{
					"preset": "sound",
					"file": "graphics-sfx.magic.lightning.bolt.impact.01",
					"options": {
						"delay": 500,
						"id": "SFX Lightning Bounce"
					}
				},
				{
					"preset": "ranged",
					"file": "jb2a.chain_lightning.primary.blue",
					"options": {
						"id": "VFX Lightning Bounce",
						"waitUntilFinished": -1000,
						"preset": {
							"bounce": {
								"file": "jb2a.chain_lightning.secondary.blue",
								"sound": {
									"id": "SFX Lightning Bounce",
									"overrides": {
										"options": {
											"delay": false
										}
									}
								}
							}
						}
					}
				}
			]
		}
	]
}
